dgmr/__init__.py
dgmr/common.py
dgmr/dgmr.py
dgmr/discriminators.py
dgmr/generators.py
dgmr/hub.py
dgmr/losses.py
dgmr/layers/Attention.py
dgmr/layers/ConvGRU.py
dgmr/layers/CoordConv.py
dgmr/layers/__init__.py
dgmr/layers/utils.py
dgmr-1.4.3.dist-info/licenses/LICENSE
dgmr-1.4.3.dist-info/METADATA
dgmr-1.4.3.dist-info/WHEEL
dgmr-1.4.3.dist-info/top_level.txt
dgmr-1.4.3.dist-info/RECORD
