Metadata-Version: 2.4
Name: dgmr
Version: 1.4.3
Summary: PyTorch Skillful Nowcasting GAN Implementation
Home-page: https://github.com/openclimatefix/skillful_nowcasting
Author: Jacob Prince-Bieker
Author-email: jacob@bieker.tech
License: MIT License
Keywords: artificial intelligence,deep learning,transformer,attention mechanism,metnet,forecasting,remote-sensing,gan
Classifier: Development Status :: 4 - Beta
Classifier: Intended Audience :: Developers
Classifier: Topic :: Scientific/Engineering :: Artificial Intelligence
Classifier: License :: OSI Approved :: MIT License
Classifier: Programming Language :: Python :: 3.6
License-File: LICENSE
Requires-Dist: torch
Requires-Dist: antialiased_cnns
Requires-Dist: pytorch_msssim
Requires-Dist: numpy
Requires-Dist: torchvision>=0.11.0
Requires-Dist: pytorch_lightning
Requires-Dist: einops
Requires-Dist: huggingface_hub>=0.23.3
Requires-Dist: safetensors
Requires-Dist: wandb
Requires-Dist: datasets
Requires-Dist: tensorflow
Dynamic: author
Dynamic: author-email
Dynamic: classifier
Dynamic: description
Dynamic: description-content-type
Dynamic: home-page
Dynamic: keywords
Dynamic: license
Dynamic: license-file
Dynamic: requires-dist
Dynamic: summary
